{
  "date_iso": "2026-07-20",
  "date_human": "Monday, July 20, 2026",
  "summary": "11 countries. The deepening US-Iran war leads coverage abroad: the US completed a ninth straight night of strikes as the American death toll reached 17 and Iran's leadership called the ceasefire worthless. The World Cup final outside New York, where Trump was booed while handing Spain the trophy over Argentina, and his revived China election-fraud claims also travel widely.",
  "countries": [
    {
      "flag": "🇫🇷",
      "name": "France",
      "region": "Western Europe",
      "items": [
        {
          "outlet": "France 24",
          "lean": "funded",
          "date": "2026-07-19",
          "title": "Greeted with boos, Trump lingers on stage to lap up World Cup spotlight",
          "url": "https://www.france24.com/en/americas/20260719-greeted-with-boos-trump-lingers-on-stage-to-lap-up-world-cup-spotlight",
          "note": "The final was played on US soil, so the crowd's reaction to the president became its own story abroad."
        },
        {
          "outlet": "France 24",
          "lean": "funded",
          "date": "2026-07-17",
          "title": "Trump accuses China of 'largest compromise' US election data, vows to declassify intelligence",
          "url": "https://www.france24.com/en/americas/20260717-trump-china-largest-compromise-us-election-data-declassify-intelligence"
        }
      ]
    },
    {
      "flag": "🇯🇵",
      "name": "Japan",
      "region": "East Asia",
      "items": [
        {
          "outlet": "The Japan Times",
          "lean": "neutral",
          "date": "2026-07-20",
          "title": "Trump is silent so far on Iran strategy as U.S. death toll hits 17",
          "url": "https://www.japantimes.co.jp/news/2026/07/20/world/politics/trump-iran-strategy-us-death/"
        },
        {
          "outlet": "The Japan Times",
          "lean": "neutral",
          "date": "2026-07-18",
          "title": "U.S. partially restores Hong Kong status revoked by Trump, drawing praise from China",
          "url": "https://www.japantimes.co.jp/news/2026/07/18/asia-pacific/politics/us-hong-kong-status-china/"
        }
      ]
    },
    {
      "flag": "🇶🇦",
      "name": "Qatar",
      "region": "Gulf",
      "items": [
        {
          "outlet": "Al Jazeera",
          "lean": "funded",
          "date": "2026-07-18",
          "title": "Iran suggests MoU 'suspended' as 50 killed in US strikes in July",
          "url": "https://www.aljazeera.com/news/2026/7/18/iran-accuses-us-of-striking-critical-infrastructure-as-war-intensifies"
        }
      ]
    },
    {
      "flag": "🇷🇺",
      "name": "Russia",
      "region": "Eurasia",
      "items": [
        {
          "outlet": "RT",
          "lean": "state",
          "date": "2026-07-20",
          "title": "Trump: Iran still has missiles, drones and production facilities",
          "url": "https://russian.rt.com/world/news/1659093-tramp-iran-moschnosti",
          "orig": "Трамп: у Ирана по-прежнему есть ракеты, БПЛА и производственные мощности",
          "note": "State television frames the admission as a sign that US strikes have not achieved their aim."
        },
        {
          "outlet": "RT",
          "lean": "state",
          "title": "Trump says strikes on Iran will continue until he personally stops them",
          "url": "https://russian.rt.com/world/news/1656936-tramp-udary-iran",
          "orig": "Трамп заявил, что удары по Ирану продолжатся, пока он лично не остановит их"
        }
      ]
    },
    {
      "flag": "🇨🇳",
      "name": "China & Hong Kong",
      "region": "East Asia",
      "items": [
        {
          "outlet": "South China Morning Post",
          "lean": "neutral",
          "title": "China and US still in contact on Xi summit trip despite Trump's election claims",
          "url": "https://www.scmp.com/news/china/diplomacy/article/3361215/china-us-talks-ahead-xi-jinpings-planned-september-visit-maintained-beijing"
        },
        {
          "outlet": "Global Times",
          "lean": "state",
          "title": "China has never and will never interfere in the presidential elections of the US: embassy tells GT",
          "url": "https://www.globaltimes.cn/page/202607/1366195.shtml"
        }
      ]
    },
    {
      "flag": "🇦🇷",
      "name": "Argentina",
      "region": "South America",
      "items": [
        {
          "outlet": "Buenos Aires Times",
          "lean": "neutral",
          "date": "2026-07-19",
          "title": "Spain shatters Argentina's dream with 1-0 win in World Cup final",
          "url": "https://batimes.com.ar/news/sports/spain-shatters-argentinas-dream-with-1-0-win-in-world-cup-final.phtml"
        },
        {
          "outlet": "Buenos Aires Times",
          "lean": "neutral",
          "title": "Outrage as FIFA's Infantino bends rules to Trump's whim at World Cup",
          "url": "https://www.batimes.com.ar/news/sports/outrage-as-fifas-infantino-bends-rules-to-trumps-whim-at-world-cup.phtml",
          "note": "Coverage from the losing finalist folds the sport into a wider unease about how the US host handled the tournament."
        }
      ]
    },
    {
      "flag": "🇰🇷",
      "name": "South Korea",
      "region": "East Asia",
      "items": [
        {
          "outlet": "The Korea Herald",
          "lean": "neutral",
          "title": "Trump administration caps how long international students can stay in the US",
          "url": "https://www.koreaherald.com/article/10811860"
        },
        {
          "outlet": "The Korea Herald",
          "lean": "neutral",
          "title": "Trump opens door to expanded US Navy partnership with Korean shipbuilders",
          "url": "https://www.koreaherald.com/article/10811275"
        }
      ]
    },
    {
      "flag": "🇿🇦",
      "name": "South Africa",
      "region": "Southern Africa",
      "items": [
        {
          "outlet": "News24",
          "lean": "neutral",
          "date": "2026-07-15",
          "title": "US Democrats block massive defence bill over Iran war frustration",
          "url": "https://www.news24.com/world/us-democrats-block-massive-defence-bill-over-iran-war-frustration-20260715-0341"
        },
        {
          "outlet": "News24",
          "lean": "neutral",
          "date": "2026-07-18",
          "title": "Bahrain, Kuwait suffer attacks as Iran war escalates with US",
          "url": "https://www.news24.com/world/bahrain-kuwait-suffer-attacks-as-iran-war-escalates-with-us-20260718-0505"
        }
      ]
    },
    {
      "flag": "🇪🇺",
      "name": "Europe",
      "region": "European Union",
      "items": [
        {
          "outlet": "Euronews",
          "lean": "neutral",
          "date": "2026-07-20",
          "title": "US hits Iran for ninth night as Khamenei calls ceasefire 'worthless'",
          "url": "https://www.euronews.com/2026/07/20/iran-launches-retaliatory-attacks-after-us-completes-ninth-night-of-strikes"
        }
      ]
    },
    {
      "flag": "🇹🇷",
      "name": "Türkiye",
      "region": "Eastern Mediterranean",
      "items": [
        {
          "outlet": "Daily Sabah",
          "lean": "progov",
          "title": "US widens assault on Iran with strikes on bridges, key port tower",
          "url": "https://www.dailysabah.com/world/mid-east/us-widens-assault-on-iran-with-strikes-on-bridges-key-port-tower"
        }
      ]
    },
    {
      "flag": "🇰🇪",
      "name": "Kenya",
      "region": "East Africa",
      "items": [
        {
          "outlet": "Daily Nation",
          "lean": "neutral",
          "title": "Trump grants last-minute work permit extensions to US immigrants",
          "url": "https://nation.africa/kenya/news/world/trump-grants-last-minute-work-permit-extensions-to-us-immigrants-5524116"
        }
      ]
    }
  ]
}